rapidata/__init__.py
rapidata/api_client_README.md
rapidata/api_client/__init__.py
rapidata/api_client/api_client.py
rapidata/api_client/api_response.py
rapidata/api_client/configuration.py
rapidata/api_client/exceptions.py
rapidata/api_client/rest.py
rapidata/api_client/api/__init__.py
rapidata/api_client/api/asset_api.py
rapidata/api_client/api/audience_api.py
rapidata/api_client/api/batch_upload_api.py
rapidata/api_client/api/benchmark_api.py
rapidata/api_client/api/campaign_api.py
rapidata/api_client/api/client_api.py
rapidata/api_client/api/coco_api.py
rapidata/api_client/api/compare_workflow_api.py
rapidata/api_client/api/customer_rapid_api.py
rapidata/api_client/api/datapoint_api.py
rapidata/api_client/api/dataset_api.py
rapidata/api_client/api/evaluation_workflow_api.py
rapidata/api_client/api/feedback_api.py
rapidata/api_client/api/grouped_ranking_workflow_api.py
rapidata/api_client/api/identity_api.py
rapidata/api_client/api/job_api.py
rapidata/api_client/api/job_definition_api.py
rapidata/api_client/api/job_revision_api.py
rapidata/api_client/api/leaderboard_api.py
rapidata/api_client/api/newsletter_api.py
rapidata/api_client/api/order_api.py
rapidata/api_client/api/participant_api.py
rapidata/api_client/api/pipeline_api.py
rapidata/api_client/api/prompt_api.py
rapidata/api_client/api/rapid_api.py
rapidata/api_client/api/rapidata_identity_api_api.py
rapidata/api_client/api/sample_api.py
rapidata/api_client/api/simple_workflow_api.py
rapidata/api_client/api/survey_api.py
rapidata/api_client/api/user_info_api.py
rapidata/api_client/api/user_rapid_api.py
rapidata/api_client/api/validation_set_api.py
rapidata/api_client/api/workflow_api.py
rapidata/api_client/models/__init__.py
rapidata/api_client/models/ab_test_selection.py
rapidata/api_client/models/ab_test_selection_a_inner.py
rapidata/api_client/models/add_campaign_artifact_result.py
rapidata/api_client/models/add_campaign_model.py
rapidata/api_client/models/add_campaign_model_user_filters_inner.py
rapidata-3.1.1.dist-info/METADATA
rapidata-3.1.1.dist-info/WHEEL
rapidata-3.1.1.dist-info/licenses/LICENSE
rapidata-3.1.1.dist-info/RECORD
