Metadata-Version: 2.4
Name: rapidata
Version: 3.1.1
Summary: Rapidata package containing the Rapidata Python Client to interact with the Rapidata Web API in an easy way.
Author-email: Rapidata AG <info@rapidata.ai>
License-Expression: Apache-2.0
License-File: LICENSE
Requires-Python: <4,>=3.10
Requires-Dist: authlib==1.6.5
Requires-Dist: colorama==0.4.6
Requires-Dist: deprecated<2,>=1.2.14
Requires-Dist: diskcache<6,>=5.6.3
Requires-Dist: hatchling>=1.28.0
Requires-Dist: httpx<0.29,>=0.28.1
Requires-Dist: opentelemetry-api>=1.27.0
Requires-Dist: opentelemetry-exporter-otlp>=1.27.0
Requires-Dist: opentelemetry-sdk>=1.27.0
Requires-Dist: packaging>=16.0.0
Requires-Dist: pandas<3,>=2.2.3
Requires-Dist: pydantic<3,>=2.8.2
Requires-Dist: pyjwt<3,>=2.9.0
Requires-Dist: python-dateutil<3,>=2.9.0.post0
Requires-Dist: requests<3,>=2.32.3
Requires-Dist: tinytag<3,>=2.0.0
Requires-Dist: tqdm<5,>=4.66.5
